{"base_css-advanced_background.md":"6fa878f9","base_css-advanced_mask.md":"ffd14ee5","base_css_transform.md":"a322b6f6","base_ts_decorators.md":"ad3557d1","base_css_select.md":"d05b084b","base_css_box-model.md":"7c0ba0fa","base_css_introduction.md":"80358c4b","base_css_layout.md":"6b246859","base_css_background.md":"ab68f110","base_regexp_stringmethods.md":"bc52a691","base_css_attributes.md":"275f97d7","base_ts_vue-class-component.md":"27ec6280","base_ts_introduction.md":"5fda6812","base_css_val.md":"8e0157a7","base_css_function.md":"664e2e18","base_css_shadow.md":"79619e13","base_css_mask.md":"2e16e12a","base_regexp_methods.md":"2fa1c217","essay_introduction_introduction.md":"7a2a6ea5","base_ts_vue-property-decorator.md":"cf413b72","essay_introduction_markdown.md":"94d9817a","essay_introduction_safety.md":"fb690c0b","essay_introduction_vp-md.md":"8588daef","index.md":"cac92bda","base_regexp_introduction.md":"5a6e86f7","project_other_package.md":"eccb3b94","project_other_project.md":"6c158544","project_other_ast.md":"e92624a0","source-code_jq_attribute.md":"8181c4e2","project_other_jest.md":"e45b171a","project_other_npm.md":"4ebaf624","source-code_jq_xhr.md":"dfd196f9","project_other_tsconfig.md":"24f9105e","project_other_introduction.md":"f4be87cb","project_webpack_build.md":"98219758","source-code_jq_queue.md":"c90e9441","source-code_jq_regular.md":"bae9fa55","source-code_jq_core.md":"3703a2ec","source-code_jq_trigger.md":"1e6674cb","source-code_jq_css.md":"00f5ab86"}
